elastic_hash/__init__.py
elastic_hash/elastic_table.py
elastic_hash/funnel_table.py
elastic_hash/hash_functions.py
open_elastic_hash-0.1.1.dist-info/LICENSE
open_elastic_hash-0.1.1.dist-info/METADATA
open_elastic_hash-0.1.1.dist-info/WHEEL
open_elastic_hash-0.1.1.dist-info/top_level.txt
open_elastic_hash-0.1.1.dist-info/RECORD
