Metadata-Version: 2.2
Name: open-elastic-hash
Version: 0.1.1
Summary: Implementation of Elastic and Funnel Hashing algorithms based on academic research
Author-email: Yurii Stenin <your.email@example.com>
License: MIT
Project-URL: Homepage, https://github.com/jorgik1/elastic-hash
Project-URL: Bug Tracker, https://github.com/jorgik1/elastic-hash/issues
Project-URL: Documentation, https://github.com/jorgik1/elastic-hash#readme
Project-URL: Changelog, https://github.com/jorgik1/elastic-hash/blob/main/CHANGELOG.md
Project-URL: Source Code, https://github.com/jorgik1/elastic-hash
Keywords: hash table,data structure,algorithm,elastic hash,funnel hash,open addressing
Classifier: Programming Language :: Python :: 3
Classifier: Programming Language :: Python :: 3.8
Classifier: Programming Language :: Python :: 3.9
Classifier: Programming Language :: Python :: 3.10
Classifier: Programming Language :: Python :: 3.11
Classifier: License :: OSI Approved :: MIT License
Classifier: Operating System :: OS Independent
Classifier: Topic :: Software Development :: Libraries
Classifier: Topic :: Software Development :: Libraries :: Python Modules
Classifier: Intended Audience :: Developers
Classifier: Intended Audience :: Science/Research
Classifier: Development Status :: 4 - Beta
Requires-Python: >=3.8
License-File: LICENSE
Provides-Extra: dev
Requires-Dist: pytest; extra == "dev"
Requires-Dist: pytest-cov; extra == "dev"
Requires-Dist: black; extra == "dev"
Requires-Dist: isort; extra == "dev"
Requires-Dist: flake8; extra == "dev"
Provides-Extra: plot
Requires-Dist: matplotlib; extra == "plot"
Provides-Extra: full
Requires-Dist: matplotlib; extra == "full"
Dynamic: requires-python
